nlp3/__init__.py
nlp3/__main__.py
nlp3/cli.py
nlp3/code_model.py
nlp3/code_query_engine.py
nlp3/core.py
nlp3/nlp.py
nlp3/spell_check.py
nlp3/universal_parser.py
nlp3/adapters/__init__.py
nlp3/adapters/code_adapter.py
nlp3/adapters/code_intelligence.py
nlp3/adapters/code_tree_adapter.py
nlp3/adapters/code_use_cases.py
nlp3/adapters/filesystem.py
nlp3/adapters/filesystem_fixed.py
nlp3/adapters/html.py
nlp3/adapters/html_adapter.py
nlp3/adapters/json_adapter.py
nlp3/adapters/semantic_search.py
nlp3/adapters/universal_code_adapter.py
nlp3/adapters/api/__init__.py
nlp3/adapters/api/rest.py
nlp3/output/__init__.py
nlp3/output/csv.py
nlp3/output/html.py
nlp3/output/markdown.py
nlp3/output/xml.py
nlp3/output/yaml.py
nlp3/search/__init__.py
nlp3/search/cache.py
nlp3/search/cli.py
nlp3/search/core.py
nlp3/search/indexing.py
nlp3/search/parsing.py
nlp3-1.0.10.dist-info/licenses/LICENSE
nlp3-1.0.10.dist-info/METADATA
nlp3-1.0.10.dist-info/WHEEL
nlp3-1.0.10.dist-info/entry_points.txt
nlp3-1.0.10.dist-info/top_level.txt
nlp3-1.0.10.dist-info/RECORD
