Metadata-Version: 2.4
Name: nlp3
Version: 1.0.10
Summary: Universal Context Navigator - Navigate any data structure using natural language
Author-email: Tom Sapletta <tom@sapletta.com>
License: Apache 2.0
Project-URL: Homepage, https://github.com/wronai/nlp3
Project-URL: Documentation, https://github.com/wronai/nlp3#readme
Project-URL: Repository, https://github.com/wronai/nlp3
Project-URL: Issues, https://github.com/wronai/nlp3/issues
Keywords: nlp,navigation,tree,filesystem,html,api,json,yaml,cli
Classifier: Development Status :: 4 - Beta
Classifier: Intended Audience :: Developers
Classifier: License :: OSI Approved :: Apache Software License
Classifier: Programming Language :: Python :: 3
Classifier: Programming Language :: Python :: 3.10
Classifier: Programming Language :: Python :: 3.11
Classifier: Programming Language :: Python :: 3.12
Classifier: Topic :: Software Development :: Testing
Classifier: Topic :: Internet :: WWW/HTTP
Requires-Python: >=3.10
License-File: LICENSE
Requires-Dist: typer>=0.9.0
Requires-Dist: rich>=13.7.0
Requires-Dist: beautifulsoup4>=4.12.0
Requires-Dist: aiohttp>=3.9.0
Requires-Dist: pyyaml>=6.0
Requires-Dist: lxml>=4.9.0
Requires-Dist: tree-sitter>=0.20.0
Requires-Dist: sentence-transformers>=2.2.0
Provides-Extra: test
Requires-Dist: pytest>=7.4.0; extra == "test"
Requires-Dist: pytest-cov>=4.1.0; extra == "test"
Requires-Dist: pytest-asyncio>=0.21.0; extra == "test"
Requires-Dist: pytest-mock>=3.10.0; extra == "test"
Provides-Extra: all
Requires-Dist: gql>=3.5.0; extra == "all"
Requires-Dist: zeep>=4.2.0; extra == "all"
Requires-Dist: xmltodict>=0.13.0; extra == "all"
Requires-Dist: redis>=5.0.0; extra == "all"
Requires-Dist: prometheus-client>=0.19.0; extra == "all"
Requires-Dist: tree-sitter-python>=0.20.0; extra == "all"
Requires-Dist: tree-sitter-javascript>=0.20.0; extra == "all"
Requires-Dist: tree-sitter-typescript>=0.20.0; extra == "all"
Requires-Dist: tree-sitter-go>=0.20.0; extra == "all"
Requires-Dist: tree-sitter-java>=0.20.0; extra == "all"
Requires-Dist: tree-sitter-rust>=0.20.0; extra == "all"
Requires-Dist: tree-sitter-cpp>=0.20.0; extra == "all"
Requires-Dist: faiss-cpu>=1.7.0; extra == "all"
Requires-Dist: hnswlib>=0.7.0; extra == "all"
Provides-Extra: dev
Requires-Dist: pytest>=7.4.0; extra == "dev"
Requires-Dist: pytest-asyncio>=0.21.0; extra == "dev"
Requires-Dist: pytest-cov>=4.1.0; extra == "dev"
Requires-Dist: black>=23.0.0; extra == "dev"
Requires-Dist: ruff>=0.1.0; extra == "dev"
Requires-Dist: mypy>=1.7.0; extra == "dev"
Dynamic: license-file
